django_entity_event_slack-1.1.0.dist-info/METADATA
django_entity_event_slack-1.1.0.dist-info/RECORD
django_entity_event_slack-1.1.0.dist-info/WHEEL
django_entity_event_slack-1.1.0.dist-info/top_level.txt
entity_event_slack/__init__.py
entity_event_slack/apps.py
entity_event_slack/constants.py
entity_event_slack/models.py
entity_event_slack/tasks.py
entity_event_slack/version.py
entity_event_slack/migrations/0001_initial.py
entity_event_slack/migrations/__init__.py
entity_event_slack/tests/__init__.py
entity_event_slack/tests/models_tests.py
entity_event_slack/tests/tasks_tests.py
