Metadata-Version: 2.1
Name: django-entity-event-slack
Version: 1.1.0
Summary: A pushable slack medium for the Django Entity Event system
Home-page: https://github.com/ambitioninc/django-entity-event-slack
Author: Wes Kendall
Author-email: opensource@ambition.com
License: MIT
Keywords: django-entity-event,slack
Platform: UNKNOWN
Classifier: Programming Language :: Python
Classifier: Programming Language :: Python :: 3.6
Classifier: Programming Language :: Python :: 3.7
Classifier: Intended Audience :: Developers
Classifier: License :: OSI Approved :: MIT License
Classifier: Operating System :: OS Independent
Classifier: Framework :: Django
Classifier: Framework :: Django :: 2.0
Classifier: Framework :: Django :: 2.1
Classifier: Framework :: Django :: 2.2
Requires-Dist: celery (>=3.1)
Requires-Dist: Django (>=2.0)
Requires-Dist: django-db-mutex (>=1.2.0)
Requires-Dist: django-entity-event (>=1.2.0)
Requires-Dist: django-manager-utils (>=1.4.0)
Requires-Dist: pyslack (>=0.1.3)
Requires-Dist: requests
